{
  "kind": "collectionType",
  "collectionName": "news",
  "info": {
    "singularName": "new",
    "pluralName": "news",
    "displayName": "New",
    "description": ""
  },
  "options": {
    "draftAndPublish": true
  },
  "pluginOptions": {},
  "attributes": {
    "title": {
      "type": "string"
    },
    "slug": {
      "type": "string"
    },
    "feature_image": {
      "type": "media",
      "multiple": true,
      "required": false,
      "allowedTypes": [
        "images",
        "files",
        "videos",
        "audios"
      ]
    },
    "category": {
      "type": "relation",
      "relation": "manyToOne",
      "target": "api::category.category",
      "inversedBy": "news"
    },
    "location": {
      "type": "relation",
      "relation": "manyToOne",
      "target": "api::location.location",
      "inversedBy": "news"
    },
    "description": {
      "type": "blocks"
    }
  }
}
